z_units-0.1.9.dist-info/METADATA
z_units-0.1.9.dist-info/WHEEL
z_units-0.1.9.dist-info/entry_points.txt
z_units-0.1.9.dist-info/licenses/LICENSE
z_units/__init__.py
z_units/constant.py
z_units/environment.py
z_units/quantity.py
z_units/unit.py
z_units/unit_registry.py
z_units/util.py
z_units-0.1.9.dist-info/RECORD
