Metadata-Version: 2.1
Name: z-units
Version: 0.1.9
Summary: A simple unit converter for chemical engineers
Author-Email: zenius <zenius@outlook.com>
License: MIT
Project-URL: Homepage, https://github.com/zxzenius/z-units
Requires-Python: >=3.7
